flexipde/__init__.py
flexipde/_version.py
flexipde/grid.py
flexipde/io.py
flexipde/optim.py
flexipde/py.typed
flexipde/run.py
flexipde/solver.py
flexipde/discretisation/__init__.py
flexipde/discretisation/finite_difference.py
flexipde/discretisation/spectral.py
flexipde/models/__init__.py
flexipde/models/advection.py
flexipde/models/base.py
flexipde/models/diffusion.py
flexipde/models/drift_kinetic.py
flexipde/models/ideal_alfven.py
flexipde/models/resistive_mhd.py
flexipde/models/two_fluid.py
flexipde/models/vlasov.py
flexipde-0.3.3.dist-info/licenses/LICENSE
flexipde-0.3.3.dist-info/METADATA
flexipde-0.3.3.dist-info/WHEEL
flexipde-0.3.3.dist-info/entry_points.txt
flexipde-0.3.3.dist-info/top_level.txt
flexipde-0.3.3.dist-info/RECORD
