Metadata-Version: 2.4
Name: flexipde
Version: 0.3.3
Summary: Flexible high‑performance plasma physics solver in Python using JAX and NumPy
Author-email: UWPlasma <uwplasma@wisc.edu>
Maintainer-email: UWPlasma <uwplasma@wisc.edu>
License-Expression: MIT
Classifier: Programming Language :: Python :: 3
Classifier: Programming Language :: Python :: 3 :: Only
Classifier: Operating System :: OS Independent
Classifier: Development Status :: 4 - Beta
Classifier: Intended Audience :: Science/Research
Classifier: Topic :: Scientific/Engineering :: Physics
Requires-Python: >=3.10
License-File: LICENSE
Requires-Dist: numpy
Requires-Dist: tomli; python_version < "3.11"
Provides-Extra: jax
Requires-Dist: jax; extra == "jax"
Requires-Dist: equinox; extra == "jax"
Requires-Dist: diffrax; extra == "jax"
Requires-Dist: optax; extra == "jax"
Requires-Dist: jaxtyping; extra == "jax"
Provides-Extra: symbolic
Requires-Dist: sympy2jax; extra == "symbolic"
Provides-Extra: docs
Requires-Dist: mkdocs-material; extra == "docs"
Requires-Dist: mkdocstrings-python; extra == "docs"
Provides-Extra: testing
Requires-Dist: pytest; extra == "testing"
Requires-Dist: pytest-cov; extra == "testing"
Requires-Dist: mypy; extra == "testing"
Dynamic: license-file
